ComplexMathFunctions/__init__.py
ComplexMathFunctions/difficult_maths.py
complexmathfunctions-1.5.dist-info/licenses/LICENSE
complexmathfunctions-1.5.dist-info/METADATA
complexmathfunctions-1.5.dist-info/WHEEL
complexmathfunctions-1.5.dist-info/top_level.txt
complexmathfunctions-1.5.dist-info/RECORD
