Metadata-Version: 2.4
Name: ComplexMathFunctions
Version: 1.5
Summary: Complex math
Author: Enes5234r
Author-email: bayintinkercadhesabi@gmail.com
License-File: LICENSE
Dynamic: author
Dynamic: author-email
Dynamic: description
Dynamic: description-content-type
Dynamic: license-file
Dynamic: summary
